{
  "version": 1,
  "serviceConfiguration": {
    "apiName": "asaapp",
    "serviceName": "AppSync",
    "defaultAuthType": {
      "mode": "AMAZON_COGNITO_USER_POOLS",
      "cognitoUserPoolId": "authasaappddd920b5"
    },
    "conflictResolution": {
      "defaultResolutionStrategy": {
        "type": "AUTOMERGE"
      }
    },
    "additionalAuthTypes": [
      {
        "mode": "API_KEY",
        "expirationTime": 365,
        "apiKeyExpirationDate": "2025-07-24T03:27:38.061Z",
        "keyDescription": "dougu-key"
      }
    ]
  }
}